gcs_cli/__init__.py
gcs_cli/helpers/load_env.py
gcs_cli/main.py
gcs_cli/repos.json
gcs_cli/utils/auth.py
gcs_cli/utils/envVariables.py
github_client_sdk/__init__.py
github_client_sdk/auth.py
github_client_sdk/client.py
github_client_sdk/comments.py
github_client_sdk/exceptions.py
github_client_sdk/issues.py
github_client_sdk/repo.py
github_client_sdk/variables.py
github_client_sdk/workflow.py
github_client_sdk-1.1.2.dist-info/LICENSE
github_client_sdk-1.1.2.dist-info/METADATA
github_client_sdk-1.1.2.dist-info/WHEEL
github_client_sdk-1.1.2.dist-info/entry_points.txt
github_client_sdk-1.1.2.dist-info/RECORD
