Metadata-Version: 2.3
Name: github-client-sdk
Version: 1.1.2
Summary: Lightweight and easy-to-use Python SDK for seamless GitHub REST API integration, automation of GitHub Actions workflows, environment variable management, and OAuth authentication.
License: MIT
Keywords: github,github api,github sdk,python sdk,api client,rest api,automation,github client,sdk,python,httpx,github actions,workflow management,oauth authentication,devops
Author: Azim Hossain Tuhin
Author-email: codeocmmerze@example.com
Requires-Python: >=3.9
Classifier: Development Status :: 4 - Beta
Classifier: Intended Audience :: Developers
Classifier: Programming Language :: Python :: 3
Classifier: Programming Language :: Python :: 3.9
Classifier: Programming Language :: Python :: 3.10
Classifier: Programming Language :: Python :: 3.11
Classifier: License :: OSI Approved :: MIT License
Classifier: Operating System :: OS Independent
Classifier: Topic :: Software Development :: Libraries
Classifier: Topic :: Software Development :: Libraries :: Application Frameworks
Classifier: Topic :: Software Development :: Libraries :: Python Modules
Classifier: Topic :: System :: Software Distribution
Classifier: Topic :: Utilities
Requires-Dist: httpx[http2] (>=0.28.1,<0.29.0)
Requires-Dist: pyloaders (>=0.0.5,<0.0.6)
Requires-Dist: rich (>=14.0.0,<15.0.0)
Requires-Dist: tabulate (>=0.9.0,<0.10.0)
Requires-Dist: typer[all] (>=0.15.4,<0.16.0)
